phdkit/__init__.py
phdkit/autoretry.py
phdkit/infix_fn.py
phdkit/prompt.py
phdkit/py.typed
phdkit/util.py
phdkit/alg/__init__.py
phdkit/alg/interval_tree.py
phdkit/alg/maple_tree.py
phdkit/batching/__init__.py
phdkit/batching/checkpoint.py
phdkit/configlib/__init__.py
phdkit/configlib/configreader.py
phdkit/configlib/configurable.py
phdkit/configlib/configurable_fn.py
phdkit/configlib/tomlreader.py
phdkit/gplot/__init__.py
phdkit/log/__init__.py
phdkit/log/logger.py
phdkit/log/notifier.py
phdkit/log/watchdog.py
phdkit/mapreduce/__init__.py
phdkit/rich/__init__.py
phdkit/rich/lenient_time_remaining.py
phdkit/rich/subshell_mod.py
phdkit-0.1.2.dist-info/METADATA
phdkit-0.1.2.dist-info/WHEEL
phdkit-0.1.2.dist-info/licenses/LICENSE
phdkit-0.1.2.dist-info/RECORD
