Metadata-Version: 2.4
Name: phdkit
Version: 0.1.2
Summary: Scripting utilities for PhD students, including logging with email notification, task batching, plotting, and more.
Author-email: Chuyang Chen <chuyangchen2018@outlook.com>
License: MIT License
License-File: LICENSE
Classifier: Development Status :: 2 - Pre-Alpha
Classifier: Intended Audience :: Developers
Classifier: Intended Audience :: Education
Classifier: Intended Audience :: Science/Research
Classifier: License :: OSI Approved :: MIT License
Classifier: Operating System :: OS Independent
Classifier: Programming Language :: Python :: 3
Classifier: Topic :: Software Development :: Libraries
Classifier: Topic :: Utilities
Requires-Python: >=3.12
Requires-Dist: click>=8.1.8
Requires-Dist: matplotlib>=3.10.3
Requires-Dist: numpy>=2.2.6
Requires-Dist: pandas>=2.2.3
Requires-Dist: rich>=14.1.0
